ads_async/__init__.py
ads_async/__main__.py
ads_async/_version.py
ads_async/constants.py
ads_async/exceptions.py
ads_async/log.py
ads_async/protocol.py
ads_async/service.py
ads_async/structs.py
ads_async/symbols.py
ads_async/utils.py
ads_async/version.py
ads_async/asyncio/__init__.py
ads_async/asyncio/client.py
ads_async/asyncio/server.py
ads_async/asyncio/utils.py
ads_async/bin/__init__.py
ads_async/bin/ads_async.py
ads_async/bin/download.py
ads_async/bin/get.py
ads_async/bin/info.py
ads_async/bin/monitor.py
ads_async/bin/route.py
ads_async/bin/utils.py
ads_async/tests/__init__.py
ads_async/tests/conftest.py
ads_async/tests/kmono.tmc
ads_async/tests/test_server.py
ads_async/tests/test_symbol.py
ads_async-0.3.1.dist-info/AUTHORS.rst
ads_async-0.3.1.dist-info/LICENSE
ads_async-0.3.1.dist-info/METADATA
ads_async-0.3.1.dist-info/WHEEL
ads_async-0.3.1.dist-info/entry_points.txt
ads_async-0.3.1.dist-info/top_level.txt
ads_async-0.3.1.dist-info/RECORD
